subhosting/__init__.py
subhosting/_base_client.py
subhosting/_client.py
subhosting/_compat.py
subhosting/_constants.py
subhosting/_exceptions.py
subhosting/_files.py
subhosting/_models.py
subhosting/_qs.py
subhosting/_resource.py
subhosting/_response.py
subhosting/_streaming.py
subhosting/_types.py
subhosting/_version.py
subhosting/py.typed
subhosting/_utils/__init__.py
subhosting/_utils/_logs.py
subhosting/_utils/_proxy.py
subhosting/_utils/_streams.py
subhosting/_utils/_sync.py
subhosting/_utils/_transform.py
subhosting/_utils/_typing.py
subhosting/_utils/_utils.py
subhosting/lib/.keep
subhosting/resources/__init__.py
subhosting/resources/databases.py
subhosting/resources/deployments/__init__.py
subhosting/resources/deployments/app_logs.py
subhosting/resources/deployments/build_logs.py
subhosting/resources/deployments/deployments.py
subhosting/resources/domains/__init__.py
subhosting/resources/domains/certificates.py
subhosting/resources/domains/domains.py
subhosting/resources/organizations/__init__.py
subhosting/resources/organizations/analytics.py
subhosting/resources/organizations/databases.py
subhosting/resources/organizations/domains.py
subhosting/resources/organizations/organizations.py
subhosting/resources/organizations/projects.py
subhosting/resources/projects/__init__.py
subhosting/resources/projects/analytics.py
subhosting/resources/projects/deployments.py
subhosting/resources/projects/projects.py
subhosting/types/__init__.py
subhosting/types/database_update_params.py
subhosting/types/deployment_redeploy_params.py
subhosting/types/domain_update_params.py
subhosting/types/organization.py
subhosting/types/project_update_params.py
subhosting/types/deployments/__init__.py
subhosting/types/deployments/app_log_get_params.py
subhosting/types/deployments/app_log_get_response.py
subhosting/types/deployments/build_log_get_response.py
subhosting/types/domains/__init__.py
subhosting/types/domains/certificate_create_params.py
subhosting-0.1.0a2.dist-info/METADATA
subhosting-0.1.0a2.dist-info/WHEEL
subhosting-0.1.0a2.dist-info/licenses/LICENSE
subhosting-0.1.0a2.dist-info/RECORD
